mkdocs_calendar/__init__.py
mkdocs_calendar/plugin.py
mkdocs_calendar_plugin-0.4.5.dist-info/METADATA
mkdocs_calendar_plugin-0.4.5.dist-info/WHEEL
mkdocs_calendar_plugin-0.4.5.dist-info/entry_points.txt
mkdocs_calendar_plugin-0.4.5.dist-info/RECORD
