Metadata-Version: 2.3
Name: mkdocs-calendar-plugin
Version: 0.4.5
Summary: An MkDocs plugin to expose calendar information to the 'extra' configuration variable.
License: Apache-2
Keywords: mkdocs,python,markdown,wiki
Author: Jacques Supcik
Author-email: jacques.supcik@hefr.ch
Requires-Python: >=3.10,<4.0
Classifier: Development Status :: 5 - Production/Stable
Classifier: Intended Audience :: Developers
Classifier: Intended Audience :: Information Technology
Classifier: License :: Other/Proprietary License
Classifier: Programming Language :: Python :: 3
Classifier: Programming Language :: Python :: 3.10
Classifier: Programming Language :: Python :: 3.11
Classifier: Programming Language :: Python :: 3.12
Classifier: Programming Language :: Python :: 3.13
Provides-Extra: test
Requires-Dist: dateparser (>=1.2.1,<2.0.0)
Requires-Dist: mkdocs (>=1.6.1,<2.0.0)
Requires-Dist: mkdocs-macros-plugin (>=1.3.7,<2.0.0) ; extra == "test"
Requires-Dist: mkdocs-material (>=9.6.3,<10.0.0) ; extra == "test"
Requires-Dist: pytz (>=2025.1,<2026.0)
Project-URL: Repository, https://github.com/supcik/mkdocs-calendar-plugin
